weeklyandmonthly/__init__.py
weeklyandmonthly/statistics.py
WeeklyAndMonthly-0.1.2.dist-info/LICENSE
WeeklyAndMonthly-0.1.2.dist-info/METADATA
WeeklyAndMonthly-0.1.2.dist-info/WHEEL
WeeklyAndMonthly-0.1.2.dist-info/top_level.txt
WeeklyAndMonthly-0.1.2.dist-info/RECORD
