Metadata-Version: 2.1
Name: WeeklyAndMonthly
Version: 0.1.2
Summary: Calculate weekly and monthly averages from a set of datapoints.
Author: Karl Berggren
License: MIT
Classifier: Programming Language :: Python
Classifier: Programming Language :: Python :: 3.9
Requires-Python: >=3.9
License-File: LICENSE
